datasets/__init__.py
datasets/dataloader.py
datasets/dataset.py
datasets/dataspliter.py
datasets/preprocess.py
evaluator/__init__.py
evaluator/metrics.py
models/__init__.py
models/model_builder.py
models/dl_models/__init__.py
models/dl_models/cola_gnn.py
models/dl_models/dl_base.py
models/dl_models/graph_builder.py
models/dl_models/gru.py
models/dl_models/lstm.py
models/dl_models/rnn.py
models/dl_models/stp.py
models/dl_models/transformer.py
models/dl_models/dl_model/__init__.py
models/dl_models/dl_model/dl_base.py
models/dl_models/dl_model/gru.py
models/dl_models/dl_model/lstm.py
models/dl_models/dl_model/rnn.py
models/dl_models/dl_model/transformer.py
models/ml_models/__init__.py
models/ml_models/arima.py
models/ml_models/ml_base.py
models/ml_models/seir.py
models/ml_models/sir.py
models/ml_models/xgb.py
visualize/__init__.py
visualize/graph_visualize.py
visualize/line_visualize.py
PyEpidemiology-0.0.1.dist-info/LICENSE
PyEpidemiology-0.0.1.dist-info/METADATA
PyEpidemiology-0.0.1.dist-info/WHEEL
PyEpidemiology-0.0.1.dist-info/top_level.txt
PyEpidemiology-0.0.1.dist-info/RECORD
